envkit/__init__.py
envkit/_env.py
envkit/py.typed
envkit-0.7.0.post1.dist-info/licenses/LICENSE
envkit-0.7.0.post1.dist-info/WHEEL
envkit-0.7.0.post1.dist-info/METADATA
envkit-0.7.0.post1.dist-info/RECORD
