Metadata-Version: 2.4
Name: envkit
Version: 0.7.0.post1
Summary: A lightweight, strongly-typed environment variable parser focused on explicit configuration and predictable behavior, inspired by environs.
Author: Théo Guérin
Author-email: Théo Guérin <contact@theo-guerin.dev>
License-Expression: MIT
License-File: LICENSE
Classifier: Development Status :: 3 - Alpha
Classifier: Intended Audience :: Developers
Classifier: License :: OSI Approved :: MIT License
Classifier: Operating System :: OS Independent
Classifier: Programming Language :: Python
Classifier: Programming Language :: Python :: 3
Classifier: Programming Language :: Python :: 3 :: Only
Classifier: Programming Language :: Python :: 3.12
Classifier: Programming Language :: Python :: 3.13
Classifier: Programming Language :: Python :: 3.14
Classifier: Typing :: Typed
Requires-Python: >=3.12
Project-URL: Homepage, https://codeberg.org/theo-guerin/envkit
Project-URL: Issues, https://codeberg.org/theo-guerin/envkit/issues
Project-URL: Repository, https://codeberg.org/theo-guerin/envkit
